b3parser/__init__.py
b3parser/b3parser.py
b3parser/linecount.py
b3parser/regex.py
b3parser-0.1.7.dist-info/LICENSE
b3parser-0.1.7.dist-info/METADATA
b3parser-0.1.7.dist-info/WHEEL
b3parser-0.1.7.dist-info/top_level.txt
b3parser-0.1.7.dist-info/RECORD
