Metadata-Version: 2.1
Name: b3parser
Version: 0.1.7
Summary: Um parser para os arquivos de histórico de cotações da B3.
Home-page: https://github.com/diogolr/b3parser
Author: Diogo L. Rebouças
Author-email: diogolr@gmail.com
License: LGPL v3
Keywords: Cotações Históricas B3 COTAHIST
Platform: UNKNOWN
Classifier: License :: OSI Approved :: GNU Lesser General Public License v3 or later (LGPLv3+)
Classifier: Programming Language :: Python :: 3 :: Only
Classifier: Programming Language :: Python :: 3.6
Classifier: Programming Language :: Python :: 3.7
Classifier: Programming Language :: Python :: 3.8
Classifier: Programming Language :: Python :: 3.9
Requires-Dist: pymongo
